nn_numpy/__init__.py
nn_numpy/data.py
nn_numpy/helpers.py
nn_numpy/layers.py
nn_numpy/loss.py
nn_numpy/nn.py
nn_numpy/optim.py
nn_numpy/tensor.py
nn_numpy/train.py
nn_numpy-0.0.1.dist-info/LICENSE
nn_numpy-0.0.1.dist-info/METADATA
nn_numpy-0.0.1.dist-info/WHEEL
nn_numpy-0.0.1.dist-info/top_level.txt
nn_numpy-0.0.1.dist-info/RECORD
