Metadata-Version: 2.1
Name: nn-numpy
Version: 0.0.1
Summary: A package which contains a simple implementation of neural network with numpy
Home-page: https://github.com/EmanuelFontelles/nn_numpy
Author: Emanuel Fontelles
Author-email: emanuelfontelles@hotmail.com
License: Copyright 2019 Emanuel Pinheir Fontelles
